terraform_guardrail/__init__.py
terraform_guardrail/generator.py
terraform_guardrail/registry_client.py
terraform_guardrail/schema.py
terraform_guardrail/cli/__init__.py
terraform_guardrail/cli/app.py
terraform_guardrail/mcp/__init__.py
terraform_guardrail/mcp/server.py
terraform_guardrail/scanner/__init__.py
terraform_guardrail/scanner/models.py
terraform_guardrail/scanner/rules.py
terraform_guardrail/scanner/scan.py
terraform_guardrail/web/__init__.py
terraform_guardrail/web/app.py
terraform_guardrail/web/static/style.css
terraform_guardrail/web/templates/index.html
terraform_guardrail-0.2.5.dist-info/licenses/LICENSE
terraform_guardrail-0.2.5.dist-info/METADATA
terraform_guardrail-0.2.5.dist-info/WHEEL
terraform_guardrail-0.2.5.dist-info/entry_points.txt
terraform_guardrail-0.2.5.dist-info/top_level.txt
terraform_guardrail-0.2.5.dist-info/RECORD
