Metadata-Version: 2.4
Name: terraform-guardrail
Version: 0.2.5
Summary: MCP-backed Terraform assistant with ephemeral-values compliance.
Author: Huzefa Husain
License: MIT
Keywords: terraform,mcp,iac,security,compliance
Classifier: Programming Language :: Python :: 3
Classifier: License :: OSI Approved :: MIT License
Classifier: Operating System :: OS Independent
Requires-Python: >=3.10
License-File: LICENSE
Requires-Dist: fastapi>=0.110
Requires-Dist: uvicorn>=0.27
Requires-Dist: typer>=0.12
Requires-Dist: rich>=13.7
Requires-Dist: python-hcl2>=4.3.4
Requires-Dist: pydantic>=2.6
Requires-Dist: requests>=2.31
Requires-Dist: jinja2>=3.1
Requires-Dist: python-multipart>=0.0.9
Requires-Dist: streamlit>=1.30
Provides-Extra: dev
Requires-Dist: pytest>=8.0; extra == "dev"
Requires-Dist: ruff>=0.3; extra == "dev"
Requires-Dist: git-cliff>=2.4.0; extra == "dev"
Dynamic: license-file
